angryexception/__init__.py
angryexception-1.0.2.dist-info/WHEEL
angryexception-1.0.2.dist-info/METADATA
angryexception-1.0.2.dist-info/RECORD
